machinetalk/__init__.py
machinetalk/protobuf/__init__.py
machinetalk/protobuf/canon_pb2.py
machinetalk/protobuf/config_pb2.py
machinetalk/protobuf/emcclass_pb2.py
machinetalk/protobuf/firmware_pb2.py
machinetalk/protobuf/jplan_pb2.py
machinetalk/protobuf/log_pb2.py
machinetalk/protobuf/message_pb2.py
machinetalk/protobuf/motcmds_pb2.py
machinetalk/protobuf/nanopb_pb2.py
machinetalk/protobuf/object_pb2.py
machinetalk/protobuf/preview_pb2.py
machinetalk/protobuf/ros_pb2.py
machinetalk/protobuf/rtapi_message_pb2.py
machinetalk/protobuf/rtapicommand_pb2.py
machinetalk/protobuf/sample_pb2.py
machinetalk/protobuf/status_pb2.py
machinetalk/protobuf/task_pb2.py
machinetalk/protobuf/test_pb2.py
machinetalk/protobuf/types_pb2.py
machinetalk/protobuf/value_pb2.py
machinetalk_protobuf-1.2.1.dist-info/LICENSE
machinetalk_protobuf-1.2.1.dist-info/METADATA
machinetalk_protobuf-1.2.1.dist-info/WHEEL
machinetalk_protobuf-1.2.1.dist-info/top_level.txt
machinetalk_protobuf-1.2.1.dist-info/RECORD
