Metadata-Version: 2.1
Name: machinetalk-protobuf
Version: 1.2.1
Summary: Protobuf Python modules for machinetalk
Home-page: https://github.com/machinekit/machinetalk-protobuf
Author: Alexander Roessler
Author-email: alex@machinekoder.com
License: MIT
Download-URL: https://github.com/machinekit/machinetalk-protobuf/archive/1.2.1.tar.gz
Keywords: protobuf machinekit motion-control hal
Platform: UNKNOWN
Classifier: Development Status :: 5 - Production/Stable
Classifier: Intended Audience :: Developers
Classifier: Topic :: Software Development :: Object Brokering
Classifier: License :: OSI Approved :: MIT License
Classifier: Programming Language :: Python :: 2
Classifier: Programming Language :: Python :: 2.7
Classifier: Programming Language :: Python :: 3
Classifier: Programming Language :: Python :: 3.3
Classifier: Programming Language :: Python :: 3.4
Classifier: Programming Language :: Python :: 3.5
Classifier: Programming Language :: Python :: 3.6
Classifier: Programming Language :: Python :: 3.7
Requires-Dist: protobuf
Provides-Extra: dev
Requires-Dist: check-manifest ; extra == 'dev'
Provides-Extra: test
Requires-Dist: coverage ; extra == 'test'
